setup.py
pygremlin/__init__.py
pygremlin/applicationgraph.py
pygremlin/assertionchecker.py
pygremlin/assertionchecker_a8.py
pygremlin/failuregenerator.py
pygremlin/failuregenerator_a8.py
pygremlin/foo.py
pygremlin/temp.py
pygremlin.egg-info/PKG-INFO
pygremlin.egg-info/SOURCES.txt
pygremlin.egg-info/dependency_links.txt
pygremlin.egg-info/not-zip-safe
pygremlin.egg-info/requires.txt
pygremlin.egg-info/top_level.txt