Metadata-Version: 1.0
Name: pygremlin
Version: 0.1.3
Summary: Python SDK for Gremlin framework
Home-page: https://github.com/ResilienceTesting/gremlinsdk-python
Author: Shriram Rajagopalan
Author-email: shriram@us.ibm.com
License: Apache 2.0
Platform: UNKNOWN
